CSIA/VarScan.v2.3.9.jar
CSIA/__init__.py
CSIA-1.6.data/scripts/CSIA
CSIA-1.6.dist-info/DESCRIPTION.rst
CSIA-1.6.dist-info/METADATA
CSIA-1.6.dist-info/RECORD
CSIA-1.6.dist-info/WHEEL
CSIA-1.6.dist-info/metadata.json
CSIA-1.6.dist-info/top_level.txt
