Metadata-Version: 2.0
Name: CSIA
Version: 1.6
Summary: CRISPR Sequence Indel Analyze
Home-page: www.calyx.biz
Author: Yingxiang Li
Author-email: xlccalyx@gmail.com
License: MIT
Download-URL: http://www.calyx.biz/uploads/2/1/9/2/21925892/csia-1.5.tar.gz
Keywords: CRISPR Sequence Indel Analyze
Platform: UNKNOWN
Classifier: Development Status :: 3 - Alpha
Classifier: Intended Audience :: Developers
Classifier: Topic :: Software Development :: Build Tools
Classifier: License :: OSI Approved :: MIT License
Classifier: Programming Language :: Python :: 2.7
